mathkat/__init__.py
mathkat/main.py
mathkat-1.2.0.dist-info/METADATA
mathkat-1.2.0.dist-info/WHEEL
mathkat-1.2.0.dist-info/top_level.txt
mathkat-1.2.0.dist-info/RECORD
